lbm_suite2p_python/__init__.py
lbm_suite2p_python/__main__.py
lbm_suite2p_python/_benchmarking.py
lbm_suite2p_python/cellpose.py
lbm_suite2p_python/cellpose_workflow.py
lbm_suite2p_python/cli.py
lbm_suite2p_python/conversion.py
lbm_suite2p_python/default_ops.py
lbm_suite2p_python/grid_search.py
lbm_suite2p_python/gui.py
lbm_suite2p_python/merging.py
lbm_suite2p_python/normcorre.py
lbm_suite2p_python/postprocessing.py
lbm_suite2p_python/run_lsp.py
lbm_suite2p_python/utils.py
lbm_suite2p_python/volume.py
lbm_suite2p_python/zplane.py
lbm_suite2p_python-2.5.3.dist-info/licenses/LICENSE.md
lbm_suite2p_python-2.5.3.dist-info/METADATA
lbm_suite2p_python-2.5.3.dist-info/WHEEL
lbm_suite2p_python-2.5.3.dist-info/entry_points.txt
lbm_suite2p_python-2.5.3.dist-info/top_level.txt
lbm_suite2p_python-2.5.3.dist-info/RECORD
