Metadata-Version: 2.4
Name: lbm_suite2p_python
Version: 2.5.3
Summary: Light Beads Microscopy Pipeline using Suite2p
License-Expression: BSD-3-Clause
Project-URL: homepage, https://github.com/MillerBrainObservatory/LBM-Suite2p-Python
Keywords: Pipeline,Numpy,Microscopy,ScanImage,Suite2p,tiff
Classifier: Development Status :: 3 - Alpha
Classifier: Intended Audience :: Science/Research
Classifier: Programming Language :: Python :: 3 :: Only
Requires-Python: <3.12.10,>=3.12.7
License-File: LICENSE.md
Requires-Dist: mbo_utilities>=2.5.1
Provides-Extra: suite2p
Requires-Dist: suite2p_mbo>=2.0.1; extra == "suite2p"
Provides-Extra: rastermap
Requires-Dist: rastermap; extra == "rastermap"
Provides-Extra: cellpose
Requires-Dist: cellpose>=4.0.6; extra == "cellpose"
Provides-Extra: torch
Requires-Dist: torch>=2.7.0; extra == "torch"
Requires-Dist: torchvision>=0.22.0; extra == "torch"
Provides-Extra: all
Requires-Dist: lbm_suite2p_python[cellpose,rastermap,suite2p,torch]; extra == "all"
Dynamic: license-file
